{
  "prepare_queue": {
    "installed": [],
    "uninstalled": []
  },
  "config_munge": {
    "files": {
      "AndroidManifest.xml": {
        "parents": {
          "/*": [
            {
              "xml": "<uses-permission android:name=\"android.permission.INTERNET\" />",
              "count": 1
            },
            {
              "xml": "<uses-permission android:name=\"android.permission.WRITE_EXTERNAL_STORAGE\" />",
              "count": 1
            },
            {
              "xml": "<uses-permission android:name=\"android.permission.READ_EXTERNAL_STORAGE\" />",
              "count": 1
            }
          ]
        }
      }
    }
  },
  "installed_plugins": {},
  "dependent_plugins": {}
}
